{"dict": [{"support": "\u8005", "head": "\u53f8\u4f1a", "instance": [{"agent": [{"arg2": null, "arg0": "\u52d5\u4f5c\u4e3b", "arg1": "\u5834\u6240", "semantic": "\u72b6\u614b\u5909\u5316\u306a\u3057\uff08\u72b6\u614b\uff09/\u72b6\u614b\u7dad\u6301/\u7dad\u6301\u30fb\u7ba1\u7406/\u904b\u55b6\u30fb\u7d71\u6cbb/\u7d71\u6cbb", "agentive": "\u53f8\u4f1a\u3059\u308b"}], "cases": [{"noun": "\u3042\u306e\u30c6\u30ec\u30d3\u756a\u7d44", "semrole": "\u4e3b\u4f53", "category": null, "part": "\u306e", "arg": "ARG1"}, {"noun": "\u592a\u90ce", "semrole": "\u5bfe\u8c61\uff08\u4eba\uff09", "category": null, "part": "\u3060", "arg": "ARG0"}]}]}, {"support": null, "head": "\u53cb\u9054", "instance": [{"cases": [{"noun": "\u79c1", "semrole": "\u4e3b\u4f53", "category": null, "part": "\u306e", "arg": "ARG1"}, {"noun": "\u82b1\u5b50\u3055\u3093", "semrole": "\u5bfe\u8c61\uff08\u4eba\uff09", "category": null, "part": "\u3060", "arg": "ARG0"}]}, {"cases": [{"noun": "\u5b66\u6821", "semrole": "\u5834\u6240", "category": null, "part": "\u306e", "arg": "ARG1"}, {"noun": "\u82b1\u5b50\u3055\u3093", "semrole": "\u5bfe\u8c61\uff08\u4eba\uff09", "category": null, "part": "\u3060", "arg": "ARG0"}]}]}, {"support": null, "head": "\u5229\u70b9", "instance": [{"cases": [{"noun": "\u3053\u306e\u53c2\u8003\u66f8", "semrole": "\u4e3b\u4f53", "category": null, "part": "\u306e", "arg": "ARG1"}, {"noun": "\u8aad\u307f\u3084\u3059\u3044\u3053\u3068", "semrole": "\u5bfe\u8c61", "category": null, "part": "\u3060", "arg": "ARG2"}]}]}, {"support": null, "head": "\u4f5c\u8005", "instance": [{"agent": [{"arg2": null, "arg0": "\u52d5\u4f5c\u4e3b", "arg1": "\u5bfe\u8c61\uff08\u751f\u6210\u7269\uff09", "semantic": "\u72b6\u614b\u5909\u5316\u3042\u308a/\u751f\u6210\u30fb\u6d88\u6ec5/\u751f\u6210\uff08\u7269\u7406\uff09/\u751f\u6210", "agentive": "\u66f8\u304f"}], "cases": [{"noun": "\u3042\u306e\u5c0f\u8aac", "semrole": "\u4e3b\u4f53", "category": null, "part": "\u306e", "arg": "ARG1"}, {"noun": "\u7530\u4e2d\u3055\u3093", "semrole": "\u5bfe\u8c61\uff08\u4eba\uff09", "category": null, "part": "\u3060", "arg": "ARG0"}]}]}]}